cookiecutter_pypackage_example/__init__.py
cookiecutter_pypackage_example/foo.py
cookiecutter_pypackage_example-0.1.1.dist-info/LICENSE
cookiecutter_pypackage_example-0.1.1.dist-info/WHEEL
cookiecutter_pypackage_example-0.1.1.dist-info/METADATA
cookiecutter_pypackage_example-0.1.1.dist-info/RECORD
