Metadata-Version: 2.1
Name: cookiecutter-pypackage-example
Version: 0.1.1
Summary: This is a template repository for Python projects that use Poetry for their dependency management.
Home-page: https://github.com/xdurana/cookiecutter-pypackage-example
Author: Xavier Duran
Author-email: fxavier.duran@gmail.com
Requires-Python: >=3.8,<3.11
Classifier: Programming Language :: Python :: 3
Classifier: Programming Language :: Python :: 3.10
Classifier: Programming Language :: Python :: 3.8
Classifier: Programming Language :: Python :: 3.9
Project-URL: Documentation, https://xdurana.github.io/cookiecutter-pypackage-example/
Project-URL: Repository, https://github.com/xdurana/cookiecutter-pypackage-example
